{
    "prepare_queue": {
        "installed": [],
        "uninstalled": []
    },
    "config_munge": {
        "files": {
            "res/xml/config.xml": {
                "parents": {
                    "/*": [
                        {
                            "xml": "<feature name=\"PowerManagement\"><param name=\"android-package\" value=\"org.apache.cordova.powermanagement.PowerManagement\" /></feature>",
                            "count": 1
                        },
                        {
                            "xml": "<feature name=\"SocialSharing\"><param name=\"android-package\" value=\"nl.xservices.plugins.SocialSharing\" /></feature>",
                            "count": 1
                        }
                    ]
                }
            },
            "AndroidManifest.xml": {
                "parents": {
                    "/*": [
                        {
                            "xml": "<uses-permission android:name=\"android.permission.WAKE_LOCK\" />",
                            "count": 1
                        },
                        {
                            "xml": "<uses-permission android:name=\"android.permission.WRITE_EXTERNAL_STORAGE\" />",
                            "count": 1
                        }
                    ]
                }
            }
        }
    },
    "installed_plugins": {
        "at.gofg.sportscomputer.powermanagement": {
            "PACKAGE_NAME": "com.orphan.amplayer"
        },
        "nl.x-services.plugins.socialsharing": {
            "PACKAGE_NAME": "com.orphan.amplayer"
        }
    },
    "dependent_plugins": {}
}